setup.py
project/classes.py
tobbywong_20231014.egg-info/PKG-INFO
tobbywong_20231014.egg-info/SOURCES.txt
tobbywong_20231014.egg-info/dependency_links.txt
tobbywong_20231014.egg-info/top_level.txt