Metadata-Version: 2.1
Name: tobbywong-20231014
Version: 0.1
Summary: My firs html project
Home-page: UNKNOWN
Author: tobbywond
Author-email: tobbywong@gmail.com
License: UNKNOWN
Platform: UNKNOWN
